pyembed_jinja2-1.1.0-py2.7-nspkg.pth
pyembed/jinja2/__init__.py
pyembed/jinja2/templates/link.html
pyembed/jinja2/templates/rich.html
pyembed/jinja2/templates/video.html
pyembed/jinja2/templates/photo.html
pyembed_jinja2-1.1.0.dist-info/metadata.json
pyembed_jinja2-1.1.0.dist-info/top_level.txt
pyembed_jinja2-1.1.0.dist-info/METADATA
pyembed_jinja2-1.1.0.dist-info/RECORD
pyembed_jinja2-1.1.0.dist-info/WHEEL
pyembed_jinja2-1.1.0.dist-info/DESCRIPTION.rst
pyembed_jinja2-1.1.0.dist-info/namespace_packages.txt
