Metadata-Version: 2.0
Name: pyembed-jinja2
Version: 1.1.0
Summary: PyEmbed plugin for rendering embeddings using Jinja2 templates
Home-page: http://pyembed.github.io
Author: Matt Thomson
Author-email: mattjohnthomson@gmail.com
License: Copyright (c) 2013 Matt Thomson
Requires-Dist: pyembed
Requires-Dist: jinja2
